css_selector_minifier/__init__.py
css_selector_minifier-2.0.dist-info/LICENSE
css_selector_minifier-2.0.dist-info/METADATA
css_selector_minifier-2.0.dist-info/WHEEL
css_selector_minifier-2.0.dist-info/top_level.txt
css_selector_minifier-2.0.dist-info/RECORD
