Metadata-Version: 2.1
Name: css-selector-minifier
Version: 2.0
Summary: Minify css selectors in css, html, js files.
Author: 0x1618 aka ctrlshifti (Maksymilian Sawicz)
Author-email: <max.sawicz@gmail.com>
Keywords: python,css,html,js,minify,css selectors,selector,selectors,minify css selectors
License-File: LICENSE
